pyfcm/__init__.py
pyfcm/algorithms.py
pyfcm/initialization.py
scikit_cmeans-0.1.dist-info/DESCRIPTION.rst
scikit_cmeans-0.1.dist-info/METADATA
scikit_cmeans-0.1.dist-info/RECORD
scikit_cmeans-0.1.dist-info/WHEEL
scikit_cmeans-0.1.dist-info/metadata.json
scikit_cmeans-0.1.dist-info/top_level.txt
skcmeans/__init__.py
skcmeans/algorithms.py
skcmeans/initialization.py
tests/algorithms/__init__.py
tests/algorithms/test_gustafsonkessel.py
tests/algorithms/test_hard.py
tests/algorithms/test_possibilistic.py
tests/algorithms/test_probabilistic.py
